{
    "title": "How to Improve Your Padel Serve? Padel Technique",
    "url": "https://youtu.be/YSCbbCYfc9Y",
    "duration": 297,
    "language": "English",
    "difficulty_level": 1,
    "topics": [
        "serve",
        "basic-technique",
        "spin",
        "beginner-essentials"
    ],
    "prerequisites": [
        "Basic grip",
        "Proper stance"
    ],
    "quality_score": 9,
    "validation_status": true,
    "sections_used": [
        {
            "topic": "Serve mechanics",
            "start_time": 16,
            "end_time": 120,
            "file_path": "README.md#session-5-serve-return"
        },
        {
            "topic": "Key target areas",
            "start_time": 210,
            "end_time": 270,
            "file_path": "README.md#session-5-serve-return"
        }
    ],
    "transcript_validation": true,
    "notes": "Excellent breakdown of the padel serve technique, focusing on simplicity and accuracy over power. Great emphasis on proper technique and practice importance.",
    "sections": [
        {
            "title": "Introduction to Effective Serve Technique",
            "start_time": 0,
            "end_time": 20,
            "description": "Introduction to the video topic: improving serve effectiveness through proper spin and speed. Clarifies that this is a commonly requested topic among padel players."
        },
        {
            "title": "Spin Limitations with Padel Rackets",
            "start_time": 20,
            "end_time": 55,
            "description": "Explanation of how padel rackets generate less spin than tennis rackets, warning against overcomplicating serves by trying to generate too much spin, which leads to errors and reduced accuracy."
        },
        {
            "title": "Proper Slice Technique",
            "start_time": 55,
            "end_time": 90,
            "description": "Demonstration of the correct amount of slice to apply on serves, emphasizing that the ball should stay low after bouncing. Shows how to position the racket head and the proper contact point at waist height."
        },
        {
            "title": "Balancing Speed and Accuracy",
            "start_time": 90,
            "end_time": 130,
            "description": "Discussion of serve speed in relation to accuracy, explaining that players should only increase speed if they can maintain accuracy. Emphasizes that a slower, more accurate serve with proper slice is more effective than a faster, less accurate one."
        },
        {
            "title": "First and Second Serve Strategy",
            "start_time": 145,
            "end_time": 190,
            "description": "Advice on differentiating between first and second serves, suggesting that recreational players can be more aggressive on first serves but need to ensure consistent technique on both serves to avoid common tournament errors."
        },
        {
            "title": "Target Areas and Effective Serving",
            "start_time": 200,
            "end_time": 245,
            "description": "Detailed explanation of the most effective serve targets: hitting toward the side glass with slice to create difficult, low bounces, and hitting down the 'T' with slice to stretch opponents out of position."
        },
        {
            "title": "Practice Methods and Progression",
            "start_time": 254,
            "end_time": 297,
            "description": "Recommendations for practice, encouraging players to take a basket of balls and repeatedly practice serve accuracy to both key target areas. Suggests starting with basic technique before progressively increasing speed and aiming for smaller targets."
        }
    ]
}